ka_uts_uts/__init__.py
ka_uts_uts/__version__.py
ka_uts_uts/py.typed
ka_uts_uts/ioc/jinja2_.py
ka_uts_uts/ioc/yaml_.py
ka_uts_uts/utils/cls.py
ka_uts_uts/utils/fnc.py
ka_uts_uts/utils/journalctl.py
ka_uts_uts/utils/pac.py
ka_uts_uts/utils/pacs.py
ka_uts_uts/utils/path.py
ka_uts_uts/utils/systemctl.py
ka_uts_uts-4.1.0.250601.dist-info/licenses/LICENSE.txt
ka_uts_uts-4.1.0.250601.dist-info/METADATA
ka_uts_uts-4.1.0.250601.dist-info/WHEEL
ka_uts_uts-4.1.0.250601.dist-info/entry_points.txt
ka_uts_uts-4.1.0.250601.dist-info/top_level.txt
ka_uts_uts-4.1.0.250601.dist-info/RECORD
